aiowc/__init__.py
aiowc/api.py
aiowc/oauth.py
aiowc/params.py
aiowc-0.2.4.dist-info/LICENSE
aiowc-0.2.4.dist-info/METADATA
aiowc-0.2.4.dist-info/WHEEL
aiowc-0.2.4.dist-info/top_level.txt
aiowc-0.2.4.dist-info/RECORD
