Metadata-Version: 2.1
Name: aiowc
Version: 0.2.4
Summary: Asynchronous Python wrapper for WooCommerce REST API
Home-page: https://github.com/vakochetkov/aiowc
Author: Vladislav Kochetkov
Author-email: Vladislav Kochetkov <vakochetkov@gmail.com>
License: MIT License
Project-URL: Homepage, https://github.com/vakochetkov/aiowc
Project-URL: Issues, https://github.com/vakochetkov/aiowc/issues
Keywords: python,woocommerce,rest,api,async,asyncio,aiohttp,wcapi
Classifier: Programming Language :: Python :: 3
Classifier: License :: OSI Approved :: MIT License
Classifier: Operating System :: OS Independent
Requires-Python: >=3.8
License-File: LICENSE
Requires-Dist: aiohttp >=3.9.3
